sugikey/__init__.py
sugikey/bokeh_sk.py
sugikey/draw.py
sugikey/examples.py
sugikey/optim.py
sugikey/processing.py
sugikey/sankey.py
sugikey/thin.py
sugikey-0.4.0.dist-info/METADATA
sugikey-0.4.0.dist-info/WHEEL
sugikey-0.4.0.dist-info/RECORD
