Metadata-Version: 2.1
Name: sugikey
Version: 0.4.0
Summary: Drawing Sankey diagrams in Python
Author: Your Name
Author-email: you@example.com
Requires-Python: >=3.9,<4.0
Classifier: Programming Language :: Python :: 3
Classifier: Programming Language :: Python :: 3.9
Classifier: Programming Language :: Python :: 3.10
Classifier: Programming Language :: Python :: 3.11
Requires-Dist: bokeh (>=3.4.0,<4.0.0)
Requires-Dist: matplotlib (>=3.8.4,<4.0.0)
Requires-Dist: networkx (>=3.0,<4.0)
Requires-Dist: openpyxl (>=3.1.2,<4.0.0)
Requires-Dist: pandas (>=2.2.1,<3.0.0)
Requires-Dist: pulp (>=2.8.0,<3.0.0)
Requires-Dist: sphinx-material (>=0.0.36,<0.0.37)
